{
  "id": {"type": "INTEGER", "comment": "기본키"},
  "created_at": {"type": "DATETIME", "comment": "생성일시"},
  "updated_at": {"type": "DATETIME", "comment": "수정일시"},
  "flight_number": {"type": "VARCHAR(10)", "comment": "항공편 번호"},
  "departure_date": {"type": "DATE", "comment": "출발 날짜"},
  "departure_time": {"type": "TIME", "comment": "출발 시간"},
  "arrival_date": {"type": "DATE", "comment": "도착 날짜"},
  "arrival_time": {"type": "TIME", "comment": "도착 시간"},
  "departure_airport": {"type": "VARCHAR(3)", "comment": "출발 공항 코드"},
  "arrival_airport": {"type": "VARCHAR(3)", "comment": "도착 공항 코드"},
  "passenger_id": {"type": "INTEGER", "comment": "승객 ID"},
  "passenger_name": {"type": "VARCHAR(100)", "comment": "승객 이름"},
  "seat_number": {"type": "VARCHAR(5)", "comment": "좌석 번호"},
  "ticket_price": {"type": "DECIMAL(10, 2)", "comment": "항공권 가격"},
  "currency": {"type": "VARCHAR(3)", "comment": "통화 단위"},
  "payment_status": {"type": "VARCHAR(20)", "comment": "결제 상태"},
  "booking_reference": {"type": "VARCHAR(20)", "comment": "예약 참조 번호"},
  "baggage_allowance": {"type": "INTEGER", "comment": "수하물 허용량(kg)"},
  "class": {"type": "VARCHAR(20)", "comment": "좌석 등급"},
  "meal_preference": {"type": "VARCHAR(50)", "comment": "기내식 선호"},
  "special_requests": {"type": "TEXT", "comment": "특별 요청 사항"}
}